<?xml version="1.0" encoding="utf-8"?>
<Dependencies>
  <ToolsetDependencies>
    <Dependency Name="Microsoft.DotNet.Arcade.Sdk" Version="8.0.0-beta.23110.3">
      <Uri>https://github.com/dotnet/arcade</Uri>
      <Sha>96d8be74c39a4765ec919ff9bebf9e0c875fc195</Sha>
      <SourceBuild RepoName="arcade" ManagedOnly="true" />
    </Dependency>
    <Dependency Name="Microsoft.SourceBuild.Intermediate.source-build-reference-packages" Version="8.0.0-alpha.1.23103.1">
      <Uri>https://github.com/dotnet/source-build-reference-packages</Uri>
      <Sha>87936395e1226e09f3fd4fb9589f3f9b7831601a</Sha>
      <SourceBuild RepoName="source-build-reference-packages" ManagedOnly="true" />
    </Dependency>
    <Dependency Name="Microsoft.SourceLink.GitHub" Version="1.2.0-beta-23109-02" CoherentParentDependency="Microsoft.DotNet.Arcade.Sdk">
      <Uri>https://github.com/dotnet/sourcelink</Uri>
      <Sha>eefa9f9ff5a7a49e6567776330ff297ae35dafd2</Sha>
      <SourceBuild RepoName="sourcelink" ManagedOnly="true" />
    </Dependency>
  </ToolsetDependencies>
</Dependencies>
